lume/__init__.py
lume/kentta.py
lume/maare.py
lume/puukko.py
lume/sarake.py
testit/__init__.py
testit/asetukset.py
testit/mallit.py
testit/models.py
testit/testit.py
testit/migrations/0001_initial.py
testit/migrations/__init__.py
django_lume-1.4.14.dist-info/METADATA
django_lume-1.4.14.dist-info/WHEEL
django_lume-1.4.14.dist-info/historia.json
django_lume-1.4.14.dist-info/top_level.txt
django_lume-1.4.14.dist-info/RECORD
